mcp_math_server/__init__.py
mcp_math_server/__main__.py
mcp_math_server/server.py
mcp_math_server-0.1.9.dist-info/METADATA
mcp_math_server-0.1.9.dist-info/WHEEL
mcp_math_server-0.1.9.dist-info/entry_points.txt
mcp_math_server-0.1.9.dist-info/top_level.txt
mcp_math_server-0.1.9.dist-info/RECORD
