Metadata-Version: 2.4
Name: mcp-math-server
Version: 0.1.9
Summary: An MCP server that provides basic math operations
Author-email: Ajinkya <your@email.com>
License-Expression: MIT
Keywords: MCP,Claude,math,AI
Classifier: Programming Language :: Python :: 3
Classifier: Operating System :: OS Independent
Classifier: Development Status :: 3 - Alpha
Classifier: Intended Audience :: Developers
Classifier: Topic :: Software Development :: Libraries
Requires-Python: >=3.10
Requires-Dist: mcp[cli]>=1.6.0
